[{"area": "BYP", "type": "QUAD", "device_name": "QUAD:BPN28:200", "unit": 46, "element_name": "QBP35", "b_max": "13.290", "polarity": "U"}, {"area": "BYP", "type": "XCOR", "device_name": "XCOR:BPN28:206", "unit": 47, "element_name": "XCBP35", "b_max": "0.024", "polarity": "B"}, {"area": "BYP", "type": "YCOR", "device_name": "YCOR:BPN28:209", "unit": 48, "element_name": "YCBP35", "b_max": "0.008", "polarity": "B"}, {"area": "BYP", "type": "QUAD", "device_name": "QUAD:BPN28:400", "unit": 49, "element_name": "QBP28", "b_max": "14.780", "polarity": "U"}, {"area": "BYP", "type": "XCOR", "device_name": "XCOR:BPN28:406", "unit": 50, "element_name": "XCBP28", "b_max": "0.008", "polarity": "B"}, {"area": "BYP", "type": "YCOR", "device_name": "YCOR:BPN28:409", "unit": 51, "element_name": "YCBP28", "b_max": "0.024", "polarity": "B"}]