[{"area": "LI21", "device_name": "QUAD:LI21:211"}, {"area": "LI21", "device_name": "QUAD:LI21:221"}, {"area": "LI21", "device_name": "QUAD:LI21:251"}, {"area": "LI21", "device_name": "QUAD:LI21:271"}, {"area": "LI21", "device_name": "QUAD:LI21:278"}, {"area": "LI21", "device_name": "QUAD:LI21:201"}, {"area": "LI21", "device_name": "QUAD:LI21:301"}, {"area": "LI21", "device_name": "QUAD:LI21:401"}, {"area": "LI21", "device_name": "QUAD:LI21:501"}, {"area": "LI21", "device_name": "QUAD:LI21:601"}, {"area": "LI21", "device_name": "QUAD:LI21:701"}, {"area": "LI21", "device_name": "QUAD:LI21:801"}, {"area": "LI21", "device_name": "QUAD:LI21:901"}, {"area": "LI21", "device_name": "QUAD:LI21:131"}, {"area": "LI21", "device_name": "QUAD:LI21:161"}, {"area": "LI21", "device_name": "QUAD:LI21:315"}, {"area": "LI21", "device_name": "QUAD:LI21:335"}, {"area": "LI21", "device_name": "QUAD:LI21:243"}]